{
  "generatedAt": "2026-06-26",
  "sourceCount": 1,
  "works": [
    [
      "absinthe",
      "Absinthe",
      "Episode I"
    ]
  ],
  "sources": [
    {
      "workSlug": "absinthe",
      "workTitle": "Absinthe",
      "episode": "Episode I",
      "sourceSlug": "email",
      "sourceTitle": "Email",
      "count": 189,
      "start": "2006-09-01T00:00:00",
      "end": "2007-01-31T23:59:00",
      "status": "supabase source_lane docs",
      "monthly": [
        {
          "month": "2006.09",
          "count": 2
        },
        {
          "month": "2006.10",
          "count": 78
        },
        {
          "month": "2006.11",
          "count": 68
        },
        {
          "month": "2006.12",
          "count": 34
        },
        {
          "month": "2007.01",
          "count": 7
        }
      ]
    }
  ]
}
